COPYING
MANIFEST.in
README.rst
setup.py
django_template_tests.egg-info/PKG-INFO
django_template_tests.egg-info/SOURCES.txt
django_template_tests.egg-info/dependency_links.txt
django_template_tests.egg-info/requires.txt
django_template_tests.egg-info/top_level.txt
template_tests/__init__.py
template_tests/models.py
template_tests/tests.py
template_tests/utils.py