Metadata-Version: 1.0
Name: django-template-tests
Version: 1.1.0
Summary: Performs some quick static analysis on your templates
Home-page: https://chris-lamb.co.uk/projects/django-template-tests
Author: Chris Lamb
Author-email: chris@chris-lamb.co.uk
License: BSD
Platform: UNKNOWN
